{"rate":40,"review":"Food was average and the service was good","name":"Akashj","email":"akashj0@gmail.com"}
{"rate":100,"review":"kujyhtgrfedws","name":"ytrew","email":"gfd@gfd.com"}
{"rate":100,"review":"POIUYTREWA","name":"OIUYTR","email":"asdfgh@g.com"}
{"rate":100,"review":"lkjhgfds","name":"kjhgfds","email":"gfdsa@ed.com"}
{"rate":100,"review":";lkjhgfd","name":"juytre","email":"gfd@gfd.com"}
{"rate":100,"review":"jkjhgfds","name":"tgrfedwsqa","email":"gfd@gfd.com"}
{"rate":100,"review":"poiuytfrdsa","name":"JHGFDSA","email":"bvcx@gfd.com"}
{"rate":100,"review":"plokijhgfdsa","name":"yutrewq","email":"gfd@gfd.com"}
{"rate":100,"review":"zxcvbn","name":"zxcvbnm","email":"bvcx@gfd.com"}
{"rate":80,"review":"jhgfdsa","name":"jhgfdsa","email":"gfd@gfd.com"}
{"rate":60,"review":"wertyuiop[","name":"sdfghjkl","email":"gfd@gfd.com"}
